lsshu/__init__.py
lsshu/config-template.py
lsshu/init-template.py
lsshu/demo/__init__.py
lsshu/demo/crud.py
lsshu/demo/main.py
lsshu/demo/model.py
lsshu/demo/schema.py
lsshu/internal/__init__.py
lsshu/internal/crud.py
lsshu/internal/db.py
lsshu/internal/depends.py
lsshu/internal/helpers.py
lsshu/internal/method.py
lsshu/internal/model.py
lsshu/internal/redis.py
lsshu/internal/schema.py
lsshu/internal/socket.py
lsshu/oauth/__init__.py
lsshu/oauth/main.py
lsshu/oauth/model.py
lsshu/oauth/annex/__init__.py
lsshu/oauth/annex/crud.py
lsshu/oauth/annex/main.py
lsshu/oauth/annex/schema.py
lsshu/oauth/permission/__init__.py
lsshu/oauth/permission/crud.py
lsshu/oauth/permission/main.py
lsshu/oauth/permission/schema.py
lsshu/oauth/role/__init__.py
lsshu/oauth/role/crud.py
lsshu/oauth/role/main.py
lsshu/oauth/role/schema.py
lsshu/oauth/user/__init__.py
lsshu/oauth/user/crud.py
lsshu/oauth/user/main.py
lsshu/oauth/user/schema.py
lsshu_cms-2.1.0.dist-info/METADATA
lsshu_cms-2.1.0.dist-info/WHEEL
lsshu_cms-2.1.0.dist-info/top_level.txt
lsshu_cms-2.1.0.dist-info/RECORD
